{
    "type": "Feature",
    "properties": {
        "name": "Chrome Hill"
    },
    "geometry": {
        "type": "Point",
        "coordinates": [
            -1.895824,
            53.202969
        ]
    }
}