{
    "type": "Feature",
    "properties": {
        "name": "Eagle Stone"
    },
    "geometry": {
        "type": "Point",
        "coordinates": [
            -1.607318,
            53.259501
        ]
    }
}