{
    "type": "Feature",
    "properties": {
        "name": "Old Woman"
    },
    "geometry": {
        "type": "Point",
        "coordinates": [
            -1.866344,
            53.436784
        ]
    }
}