{
    "type": "Feature",
    "properties": {
        "name": "Hope Woodlands"
    },
    "geometry": {
        "type": "Point",
        "coordinates": [
            -1.788992,
            53.402806
        ]
    }
}