{
    "type": "Feature",
    "properties": {
        "name": "Rookery Wood"
    },
    "geometry": {
        "type": "Point",
        "coordinates": [
            -2.079911,
            53.186926
        ]
    }
}