{
    "type": "Feature",
    "properties": {
        "name": "Parkhouse Hill"
    },
    "geometry": {
        "type": "Point",
        "coordinates": [
            -1.882333,
            53.19981
        ]
    }
}