{
    "type": "Feature",
    "properties": {
        "name": "Shining Tor"
    },
    "geometry": {
        "type": "Point",
        "coordinates": [
            -2.009584,
            53.260728
        ]
    }
}