{
    "type": "Feature",
    "properties": {
        "name": "Buxton"
    },
    "geometry": {
        "type": "Point",
        "coordinates": [
            -1.92149,
            53.258454
        ]
    }
}