{
    "type": "Feature",
    "properties": {
        "name": "The Dales"
    },
    "geometry": {
        "type": "Point",
        "coordinates": [
            -1.702755,
            53.100913
        ]
    }
}